pygeohash/__init__.py
pygeohash/bounding_box.py
pygeohash/distances.py
pygeohash/geohash.py
pygeohash/geohash_types.py
pygeohash/logging.py
pygeohash/neighbor.py
pygeohash/stats.py
pygeohash/types.py
pygeohash/viz.py
pygeohash/cgeohash/__init__.py
pygeohash/cgeohash/geohash_module.c
pygeohash/cgeohash/geohash_module.cpython-311-x86_64-linux-gnu.so
pygeohash/cgeohash/geohash_module.pyi
pygeohash/cgeohash/setup.py
pygeohash-3.2.2.dist-info/METADATA
pygeohash-3.2.2.dist-info/WHEEL
pygeohash-3.2.2.dist-info/top_level.txt
pygeohash-3.2.2.dist-info/RECORD
pygeohash-3.2.2.dist-info/licenses/LICENSE.txt
