Metadata-Version: 2.1
Name: pygeohash
Version: 3.2.2
Summary: Python module for interacting with geohashes
Author-email: Will McGinnis <will@mcginniscommawill.com>
License: MIT
Project-URL: Homepage, https://pygeohash.mcginniscommawill.com
Project-URL: Bug Tracker, https://github.com/wdm0006/pygeohash/issues
Project-URL: Download, https://github.com/wdm0006/pygeohash/tarball/3.2.0
Keywords: geohash,gis
Classifier: Development Status :: 3 - Alpha
Classifier: Intended Audience :: Developers
Classifier: Programming Language :: Python :: 3
Classifier: License :: OSI Approved :: MIT License
Requires-Python: >=3.8
License-File: LICENSE.txt
Provides-Extra: dev
Requires-Dist: pytest>=7.0.0; extra == "dev"
Requires-Dist: pytest-cov>=4.0.0; extra == "dev"
Requires-Dist: ruff>=0.0.262; extra == "dev"
Requires-Dist: tox>=4.0.0; extra == "dev"
Requires-Dist: sphinx>=6.0.0; extra == "dev"
Requires-Dist: sphinx-rtd-theme>=1.0.0; extra == "dev"
Requires-Dist: sphinx-rtd-dark-mode>=1.3.0; extra == "dev"
Requires-Dist: sphinxcontrib-googleanalytics>=0.4; extra == "dev"
Requires-Dist: build>=0.10.0; extra == "dev"
Requires-Dist: twine>=4.0.0; extra == "dev"
Requires-Dist: pytest-benchmark; extra == "dev"
Requires-Dist: matplotlib>=3.5.0; extra == "dev"
Requires-Dist: folium>=0.14.0; extra == "dev"
Requires-Dist: requests>=2.28.0; extra == "dev"
Requires-Dist: mypy>=1.8.0; extra == "dev"
Requires-Dist: types-requests>=2.31.0; extra == "dev"
Requires-Dist: types-setuptools>=69.0.0; extra == "dev"
Requires-Dist: pandas; extra == "dev"
Requires-Dist: pandas-stubs; extra == "dev"
Requires-Dist: numpy; extra == "dev"
Requires-Dist: mutmut>=2.4.4; extra == "dev"
Provides-Extra: viz
Requires-Dist: matplotlib>=3.5.0; extra == "viz"
Requires-Dist: folium>=0.14.0; extra == "viz"
